setup.cfg
setup.py
beautifulsoupselect/__init__.py
beautifulsoupselect/soupselect.py
beautifulsoupselect.egg-info/PKG-INFO
beautifulsoupselect.egg-info/SOURCES.txt
beautifulsoupselect.egg-info/dependency_links.txt
beautifulsoupselect.egg-info/not-zip-safe
beautifulsoupselect.egg-info/requires.txt
beautifulsoupselect.egg-info/top_level.txt