Metadata-Version: 1.0
Name: beautifulsoupselect
Version: 0.2
Summary: Simple wrapper to integrate BeautifulSoup and soupselect.py in a single package
Home-page: http://github.com/sbma44/beautifulsoupselect
Author: Tom Lee
Author-email: thomas.j.lee@gmail.com
License: MIT
Platform: UNKNOWN
